timothy_gomoku/__init__.py
timothy_gomoku/classes/Gomoku_env.py
timothy_gomoku/classes/Gomoku_net.py
timothy_gomoku/classes/__init__.py
timothy_gomoku/func/__init__.py
timothy_gomoku/func/play_with_human.py
timothy_gomoku/func/print_log.py
timothy_gomoku/func/store_transition.py
timothy_gomoku-0.0.11.dist-info/licenses/LICENSE
timothy_gomoku-0.0.11.dist-info/METADATA
timothy_gomoku-0.0.11.dist-info/WHEEL
timothy_gomoku-0.0.11.dist-info/top_level.txt
timothy_gomoku-0.0.11.dist-info/RECORD
